Metadata-Version: 2.1
Name: LIST-OF-LOCATIONS
Version: 0.0.1
Summary: A tool for the location of the techmanpy robot
Home-page: UNKNOWN
Author: Arjan van der Knaap
Author-email: 18103677@student.hhs.nl
License: MIT
Keywords: Techmanpy
Platform: UNKNOWN
Classifier: Development Status :: 5 - Production/Stable
Classifier: Intended Audience :: Education
Classifier: Operating System :: Microsoft :: Windows :: Windows 10
Classifier: License :: OSI Approved :: MIT License
Classifier: Programming Language :: Python :: 3
License-File: LICENCE.txt
